ml2/__init__.py
ml2/artifact.py
ml2/configurable.py
ml2/gcp_bucket.py
ml2/globals.py
ml2/loading.py
ml2/registry.py
ml2/aiger/__init__.py
ml2/aiger/aiger_circuit.py
ml2/aiger/aiger_tokenizer.py
ml2/aiger/aiger_utils.py
ml2/data_gen/__init__.py
ml2/data_gen/counting_data_gen_server.py
ml2/data_gen/data_gen_args.py
ml2/data_gen/data_gen_server.py
ml2/data_gen/data_server.py
ml2/data_gen/progress_actor.py
ml2/data_gen/progress_bar.py
ml2/datasets/__init__.py
ml2/datasets/csv_dataset.py
ml2/datasets/csv_dataset_writer.py
ml2/datasets/dataset.py
ml2/datasets/dataset_writer.py
ml2/datasets/generator_dataset.py
ml2/datasets/load_dataset.py
ml2/datasets/split_dataset.py
ml2/datasets/split_dataset_writer.py
ml2/datasets/stats.py
ml2/datasets/utils.py
ml2/dtypes/__init__.py
ml2/dtypes/binary_ast.py
ml2/dtypes/binary_expr.py
ml2/dtypes/cat.py
ml2/dtypes/cat_seq.py
ml2/dtypes/csv_dict.py
ml2/dtypes/csv_dtype.py
ml2/dtypes/csv_dtype_with_id.py
ml2/dtypes/decomp_binary_expr.py
ml2/dtypes/decomp_binary_expr_pair.py
ml2/dtypes/decomp_dtype.py
ml2/dtypes/dtype.py
ml2/dtypes/hashable.py
ml2/dtypes/pair.py
ml2/dtypes/seq.py
ml2/dtypes/string.py
ml2/dtypes/supervised.py
ml2/dtypes/tree.py
ml2/dtypes/validation_result.py
ml2/experiment/__init__.py
ml2/experiment/experiment.py
ml2/experiment/run.py
ml2/grpc/__init__.py
ml2/grpc/aalta/__init__.py
ml2/grpc/aalta/aalta_pb2.py
ml2/grpc/aalta/aalta_pb2.pyi
ml2/grpc/aalta/aalta_pb2_grpc.py
ml2/grpc/abc_aiger/__init__.py
ml2/grpc/abc_aiger/abc_aiger_pb2.py
ml2/grpc/abc_aiger/abc_aiger_pb2.pyi
ml2/grpc/abc_aiger/abc_aiger_pb2_grpc.py
ml2/grpc/aiger/__init__.py
ml2/grpc/aiger/aiger_pb2.py
ml2/grpc/aiger/aiger_pb2.pyi
ml2/grpc/aiger/aiger_pb2_grpc.py
ml2/grpc/booleforce/__init__.py
ml2/grpc/booleforce/booleforce_pb2.py
ml2/grpc/booleforce/booleforce_pb2.pyi
ml2/grpc/booleforce/booleforce_pb2_grpc.py
ml2/grpc/bosy/__init__.py
ml2/grpc/bosy/bosy_pb2.py
ml2/grpc/bosy/bosy_pb2.pyi
ml2/grpc/bosy/bosy_pb2_grpc.py
ml2/grpc/limboole/__init__.py
ml2-0.2.1.dist-info/licenses/LICENSE
ml2-0.2.1.dist-info/METADATA
ml2-0.2.1.dist-info/WHEEL
ml2-0.2.1.dist-info/top_level.txt
ml2-0.2.1.dist-info/RECORD
