Metadata-Version: 2.4
Name: ml2
Version: 0.2.1
Summary: Machine Learning for Mathematics and Logics
Home-page: https://github.com/reactive-systems/ml2
License: MIT License
Keywords: machine learning,deep learning,mathematics,logics,neural-symbolic,system 2
Classifier: Development Status :: 2 - Pre-Alpha
Classifier: Intended Audience :: Science/Research
Classifier: License :: OSI Approved :: MIT License
Classifier: Natural Language :: English
Classifier: Programming Language :: Python :: 3.11
Classifier: Topic :: Scientific/Engineering :: Artificial Intelligence
Requires-Python: >=3.11
License-File: LICENSE
Requires-Dist: docker
Requires-Dist: google-cloud-storage
Requires-Dist: grpcio-tools; platform_machine != "arm64" or platform_system != "Darwin"
Requires-Dist: grpcio-tools==1.62.3; platform_machine == "arm64" and platform_system == "Darwin"
Requires-Dist: protobuf==4.25.5; platform_machine == "arm64" and platform_system == "Darwin"
Requires-Dist: grpcio
Requires-Dist: matplotlib
Requires-Dist: nltk
Requires-Dist: numpy; platform_machine != "arm64" or platform_system != "Darwin"
Requires-Dist: numpy<2.0; platform_machine == "arm64" and platform_system == "Darwin"
Requires-Dist: pandas
Requires-Dist: sly
Requires-Dist: tqdm
Requires-Dist: wandb
Provides-Extra: jp
Requires-Dist: jupyter; extra == "jp"
Provides-Extra: pt
Requires-Dist: torch; extra == "pt"
Provides-Extra: tf
Requires-Dist: tensorflow>=2.13; (platform_machine != "arm64" or platform_system != "Darwin") and extra == "tf"
Requires-Dist: tensorflow==2.14; (platform_machine == "arm64" and platform_system == "Darwin") and extra == "tf"
Requires-Dist: tensorflow-metal==1.1.0; (platform_machine == "arm64" and platform_system == "Darwin") and extra == "tf"
Provides-Extra: tf-legacy
Requires-Dist: tensorflow<2.12,>=2.10.0; (platform_machine != "arm64" or platform_system != "Darwin") and extra == "tf-legacy"
Requires-Dist: tensorflow-macos<2.12,>=2.10.0; (platform_machine == "arm64" and platform_system == "Darwin") and extra == "tf-legacy"
Provides-Extra: hf
Requires-Dist: datasets; extra == "hf"
Requires-Dist: transformers; extra == "hf"
Provides-Extra: ray
Requires-Dist: ray[default,tune]; extra == "ray"
Provides-Extra: full
Requires-Dist: ml2[hf,jp,pt,ray,tf]; extra == "full"
Provides-Extra: dev
Requires-Dist: black; extra == "dev"
Requires-Dist: flake8; extra == "dev"
Requires-Dist: flake8-quotes; extra == "dev"
Requires-Dist: grpcio-tools; extra == "dev"
Requires-Dist: isort; extra == "dev"
Requires-Dist: mypy; extra == "dev"
Requires-Dist: mypy-protobuf; extra == "dev"
Requires-Dist: pre-commit; extra == "dev"
Requires-Dist: pytest; extra == "dev"
Requires-Dist: rbql; extra == "dev"
Requires-Dist: rstcheck; extra == "dev"
Requires-Dist: sphinx==4.0.2; extra == "dev"
Provides-Extra: package
Requires-Dist: setuptools>=46.4; extra == "package"
Requires-Dist: wheel; extra == "package"
Requires-Dist: build; extra == "package"
Requires-Dist: twine; extra == "package"
Dynamic: license-file
